Metadata-Version: 2.1
Name: notlar
Version: 0.12
Author: Adrian Fusco
Classifier: License :: OSI Approved :: Apache Software License
Classifier: Programming Language :: Python :: 3.10
Requires-Dist: aniso8601==9.0.1
Requires-Dist: Babel==2.13.1
Requires-Dist: blinker==1.7.0
Requires-Dist: cachetools==5.3.2
Requires-Dist: certifi==2023.11.17
Requires-Dist: chardet==5.2.0
Requires-Dist: charset-normalizer==3.3.2
Requires-Dist: click==8.1.7
Requires-Dist: colorama==0.4.6
Requires-Dist: distlib==0.3.8
Requires-Dist: filelock==3.13.1
Requires-Dist: flake8==6.1.0
Requires-Dist: Flask==2.3.0
Requires-Dist: Flask-Babel==2.0.0
Requires-Dist: Flask-JWT-Extended==4.5.3
Requires-Dist: Flask-Login==0.6.2
Requires-Dist: Flask-RESTful==0.3.9
Requires-Dist: Flask-SQLAlchemy==3.1.1
Requires-Dist: greenlet==3.0.1
Requires-Dist: gunicorn==21.2.0
Requires-Dist: idna==3.6
Requires-Dist: importlib-metadata==7.0.0
Requires-Dist: itsdangerous==2.1.2
Requires-Dist: Jinja2==3.1.2
Requires-Dist: MarkupSafe==2.1.3
Requires-Dist: packaging==23.2
Requires-Dist: pathspec==0.12.1
Requires-Dist: platformdirs==4.1.0
Requires-Dist: pluggy==1.3.0
Requires-Dist: psycopg2-binary==2.9.1
Requires-Dist: pybabel==0.0.0.dev0
Requires-Dist: pycodestyle==2.11.1
Requires-Dist: pyflakes==3.1.0
Requires-Dist: PyJWT==2.8.0
Requires-Dist: pyproject-api==1.6.1
Requires-Dist: python-dotenv==1.0.0
Requires-Dist: pytz==2023.3.post1
Requires-Dist: PyYAML==6.0.1
Requires-Dist: requests==2.31.0
Requires-Dist: resend==0.6.0
Requires-Dist: six==1.16.0
Requires-Dist: SpeechRecognition==3.10.1
Requires-Dist: SQLAlchemy==2.0.23
Requires-Dist: tomli==2.0.1
Requires-Dist: tox==4.11.4
Requires-Dist: typing_extensions==4.8.0
Requires-Dist: urllib3==2.1.0
Requires-Dist: virtualenv==20.25.0
Requires-Dist: Werkzeug==2.3.0
Requires-Dist: yamllint==1.33.0
Requires-Dist: zipp==3.17.0
Requires-Dist: Pillow==10.1.0
